chinadata/__init__.py
chinadata/ca_data.py
chinadata/example.py
chinadata-0.4.1.dist-info/METADATA
chinadata-0.4.1.dist-info/WHEEL
chinadata-0.4.1.dist-info/top_level.txt
chinadata-0.4.1.dist-info/RECORD
