Metadata-Version: 2.1
Name: chinadata
Version: 0.4.1
Author: xc
Author-email: utyu@gmail.com
Platform: any
Requires-Dist: requests
Requires-Dist: pandas
